tzafon/__init__.py
tzafon/_base_client.py
tzafon/_client.py
tzafon/_compat.py
tzafon/_constants.py
tzafon/_exceptions.py
tzafon/_files.py
tzafon/_models.py
tzafon/_qs.py
tzafon/_resource.py
tzafon/_response.py
tzafon/_streaming.py
tzafon/_types.py
tzafon/_version.py
tzafon/py.typed
tzafon/_utils/__init__.py
tzafon/_utils/_compat.py
tzafon/_utils/_datetime_parse.py
tzafon/_utils/_logs.py
tzafon/_utils/_proxy.py
tzafon/_utils/_reflection.py
tzafon/_utils/_resources_proxy.py
tzafon/_utils/_streams.py
tzafon/_utils/_sync.py
tzafon/_utils/_transform.py
tzafon/_utils/_typing.py
tzafon/_utils/_utils.py
tzafon/lib/.keep
tzafon/lib/__init__.py
tzafon/lib/result_types.py
tzafon/lib/wrapper.py
tzafon/resources/__init__.py
tzafon/resources/computers/__init__.py
tzafon/resources/computers/computers.py
tzafon/resources/computers/tabs.py
tzafon/types/__init__.py
tzafon/types/computer_capture_screenshot_params.py
tzafon/types/computer_capture_screenshot_response.py
tzafon/types/computer_click_params.py
tzafon/types/computer_click_response.py
tzafon/types/computer_create_params.py
tzafon/types/computer_create_response.py
tzafon/types/computer_debug_params.py
tzafon/types/computer_debug_response.py
tzafon/types/computer_double_click_params.py
tzafon/types/computer_double_click_response.py
tzafon/types/computer_drag_params.py
tzafon/types/computer_drag_response.py
tzafon/types/computer_execute_action_params.py
tzafon/types/computer_execute_action_response.py
tzafon/types/computer_execute_batch_params.py
tzafon/types/computer_execute_batch_response.py
tzafon/types/computer_get_html_params.py
tzafon/types/computer_get_html_response.py
tzafon/types/computer_keep_alive_response.py
tzafon/types/computer_key_down_params.py
tzafon/types/computer_key_down_response.py
tzafon/types/computer_key_up_params.py
tzafon/types/computer_key_up_response.py
tzafon/types/computer_list_response.py
tzafon/types/computer_mouse_down_params.py
tzafon/types/computer_mouse_down_response.py
tzafon-2.10.0.dist-info/METADATA
tzafon-2.10.0.dist-info/WHEEL
tzafon-2.10.0.dist-info/licenses/LICENSE
tzafon-2.10.0.dist-info/RECORD
